gamesir_t1d/__init__.py
gamesir_t1d/controller.py
gamesir_t1d/examples/pygame_example.py
gamesir_t1d/tools/__init__.py
gamesir_t1d/tools/ble_scanner.py
gamesir_t1d-0.1.3.dist-info/METADATA
gamesir_t1d-0.1.3.dist-info/WHEEL
gamesir_t1d-0.1.3.dist-info/entry_points.txt
gamesir_t1d-0.1.3.dist-info/licenses/LICENSE
gamesir_t1d-0.1.3.dist-info/RECORD
