Metadata-Version: 2.4
Name: gamesir-t1d
Version: 0.1.3
Summary: Python interface for GameSir T1d controller with pygame compatibility
Project-URL: Homepage, https://github.com/pors/gamesir-t1d
Project-URL: Bug Tracker, https://github.com/pors/gamesir-t1d/issues
Author-email: Mark Pors <mark@pors.net>
License-File: LICENSE
Classifier: License :: OSI Approved :: MIT License
Classifier: Operating System :: OS Independent
Classifier: Programming Language :: Python :: 3
Classifier: Topic :: Games/Entertainment
Classifier: Topic :: Software Development :: Libraries
Requires-Python: >=3.9
Requires-Dist: bleak>=0.22.3
Requires-Dist: pygame>=2.6.1
